tripod_lambda.py
tripod_lambda-0.1.0.dist-info/entry_points.txt
tripod_lambda-0.1.0.dist-info/LICENSE
tripod_lambda-0.1.0.dist-info/WHEEL
tripod_lambda-0.1.0.dist-info/METADATA
tripod_lambda-0.1.0.dist-info/RECORD
