Metadata-Version: 2.1
Name: tripod-lambda
Version: 0.1.0
Summary: really lightweight scaffolding for lambda
License: MIT
Author: James Turk
Author-email: dev@jamesturk.net
Requires-Python: >=3.7,<4.0
Classifier: License :: OSI Approved :: MIT License
Classifier: Programming Language :: Python :: 3
Classifier: Programming Language :: Python :: 3.7
Classifier: Programming Language :: Python :: 3.8
Requires-Dist: attrs (>=19.3.0,<20.0.0)
Requires-Dist: boto3 (>=1.13.18,<2.0.0)
Requires-Dist: click (>=7.1.1,<8.0.0)
Requires-Dist: pyyaml (>=5.3.1,<6.0.0)
